azurepg_entra/__init__.py
azurepg_entra/core.py
azurepg_entra/errors.py
azurepg_entra/py.typed
azurepg_entra/psycopg2/__init__.py
azurepg_entra/psycopg2/entra_connection.py
azurepg_entra/psycopg3/__init__.py
azurepg_entra/psycopg3/async_entra_connection.py
azurepg_entra/psycopg3/entra_connection.py
azurepg_entra/sqlalchemy/__init__.py
azurepg_entra/sqlalchemy/async_entra_connection.py
azurepg_entra/sqlalchemy/entra_connection.py
azurepg_entra-0.0.1.dist-info/METADATA
azurepg_entra-0.0.1.dist-info/WHEEL
azurepg_entra-0.0.1.dist-info/top_level.txt
azurepg_entra-0.0.1.dist-info/RECORD
