Metadata-Version: 2.4
Name: azurepg-entra
Version: 0.0.1
Summary: Enable persistent connections to Azure PostgreSQL via Entra ID and automated token refresh
Author-email: Arjun Narendra <v-anarendra@microsoft.com>
License: MIT
Project-URL: Homepage, https://github.com/v-anarendra_microsoft/entra-id-integration-for-drivers
Project-URL: Issues, https://github.com/v-anarendra_microsoft/entra-id-integration-for-drivers/issues
Classifier: Programming Language :: Python :: 3
Classifier: License :: OSI Approved :: MIT License
Classifier: Operating System :: OS Independent
Requires-Python: >=3.10
Requires-Dist: azure-identity>=1.13.0
Requires-Dist: azure-core>=1.24.0
Provides-Extra: psycopg3
Requires-Dist: psycopg[binary]>=3.1.0; extra == "psycopg3"
Requires-Dist: aiohttp>=3.8.0; extra == "psycopg3"
Provides-Extra: psycopg2
Requires-Dist: psycopg2-binary>=2.9.0; extra == "psycopg2"
Provides-Extra: sqlalchemy
Requires-Dist: sqlalchemy>=2.0.0; extra == "sqlalchemy"
Requires-Dist: aiohttp>=3.8.0; extra == "sqlalchemy"
Provides-Extra: dev
Requires-Dist: pytest>=7.0.0; extra == "dev"
Requires-Dist: pytest-asyncio>=0.21.0; extra == "dev"
Requires-Dist: python-dotenv>=1.0.0; extra == "dev"
Requires-Dist: mypy~=1.15; extra == "dev"
Requires-Dist: ruff>=0.8.0; extra == "dev"
Requires-Dist: types-psycopg2>=2.9.0; extra == "dev"
Requires-Dist: psycopg-pool>=3.1.0; extra == "dev"
Provides-Extra: all
Requires-Dist: psycopg[binary]>=3.1.0; extra == "all"
Requires-Dist: aiohttp>=3.8.0; extra == "all"
Requires-Dist: psycopg2-binary>=2.9.0; extra == "all"
Requires-Dist: sqlalchemy>=2.0.0; extra == "all"
Requires-Dist: pytest>=7.0.0; extra == "all"
Requires-Dist: pytest-asyncio>=0.21.0; extra == "all"
Requires-Dist: python-dotenv>=1.0.0; extra == "all"
Requires-Dist: mypy~=1.15; extra == "all"
Requires-Dist: ruff>=0.8.0; extra == "all"
Requires-Dist: types-psycopg2>=2.9.0; extra == "all"
Requires-Dist: psycopg-pool>=3.1.0; extra == "all"
